LICENSE
MANIFEST.in
README.md
setup.py
djangoshop_stripe.egg-info/PKG-INFO
djangoshop_stripe.egg-info/SOURCES.txt
djangoshop_stripe.egg-info/dependency_links.txt
djangoshop_stripe.egg-info/not-zip-safe
djangoshop_stripe.egg-info/requires.txt
djangoshop_stripe.egg-info/top_level.txt
shop_stripe/__init__.py
shop_stripe/context_processors.py
shop_stripe/models.py
shop_stripe/modifiers.py
shop_stripe/payment.py
shop_stripe/workflows.py
shop_stripe/locale/de/LC_MESSAGES/django.mo
shop_stripe/locale/de/LC_MESSAGES/django.po
shop_stripe/static/shop/icons/stripe-solid-dark.png
shop_stripe/static/shop/icons/stripe-solid-dark@2x.png
shop_stripe/static/shop/icons/stripe-solid-dark@3x.png
shop_stripe/static/shop/icons/stripe-solid-light.png
shop_stripe/static/shop/icons/stripe-solid-light@2x.png
shop_stripe/static/shop/icons/stripe-solid-light@3x.png
shop_stripe/static/shop/js/angular-stripe.js
shop_stripe/static/shop/js/stripe.js
shop_stripe/templates/shop/stripe-creditcard-form.html